hockey_api/__init__.py
hockey_api/nhl/__init__.py
hockey_api/nhl/html_scraper.py
hockey_api/nhl/json_scraper.py
hockey_api/nhl/merge_data.py
hockey_api/nhl/schedule_scraper.py
hockey_api/nhl/scraper.py
hockey_api/nhl/utils.py
hockey_api-0.1.1.dist-info/LICENSE
hockey_api-0.1.1.dist-info/METADATA
hockey_api-0.1.1.dist-info/WHEEL
hockey_api-0.1.1.dist-info/RECORD
