Metadata-Version: 2.1
Name: hockey-api
Version: 0.1.1
Summary: Scraper for ice hockey data
Home-page: https://github.com/Safvenberger/hockey-api
License: GPL-3.0
Keywords: scraping,hockey,sports analytics
Author: Rasmus Säfvenberg
Author-email: rasmus.safvenberg@gmail.com
Requires-Python: >=3.7,<4.0
Classifier: License :: OSI Approved :: GNU General Public License v3 (GPLv3)
Classifier: Programming Language :: Python :: 3
Classifier: Programming Language :: Python :: 3.7
Classifier: Programming Language :: Python :: 3.8
Classifier: Programming Language :: Python :: 3.9
Classifier: Programming Language :: Python :: 3.10
Classifier: Programming Language :: Python :: 3.11
Requires-Dist: numpy (>=1.22.3,<2.0.0)
Requires-Dist: pandas (>=1.3.4,<2.0.0)
Requires-Dist: pandera (>=0.9.0,<0.10.0)
Requires-Dist: requests (>=2.26.0,<3.0.0)
Requires-Dist: selectolax (>=0.3.11,<0.4.0)
Requires-Dist: tqdm (>=4.64.1,<5.0.0)
Project-URL: Repository, https://github.com/Safvenberger/hockey-api
